README.md
setup.py
centreon_sdk/__init__.py
centreon_sdk/centreon.py
centreon_sdk.egg-info/PKG-INFO
centreon_sdk.egg-info/SOURCES.txt
centreon_sdk.egg-info/dependency_links.txt
centreon_sdk.egg-info/requires.txt
centreon_sdk.egg-info/top_level.txt
centreon_sdk/network/__init__.py
centreon_sdk/network/network.py
centreon_sdk/objects/__init__.py
centreon_sdk/objects/base/__init__.py
centreon_sdk/objects/base/acl_action.py
centreon_sdk/objects/base/acl_group.py
centreon_sdk/objects/base/acl_menu.py
centreon_sdk/objects/base/acl_resource.py
centreon_sdk/objects/base/cent_broker_cfg.py
centreon_sdk/objects/base/cent_engine_cfg.py
centreon_sdk/objects/base/cmd.py
centreon_sdk/objects/base/contact.py
centreon_sdk/objects/base/contact_group.py
centreon_sdk/objects/base/contact_template.py
centreon_sdk/objects/base/dependency.py
centreon_sdk/objects/base/downtime.py
centreon_sdk/objects/base/general.py
centreon_sdk/objects/base/host.py
centreon_sdk/objects/base/host_category.py
centreon_sdk/objects/base/host_group.py
centreon_sdk/objects/base/host_group_service.py
centreon_sdk/objects/base/host_status.py
centreon_sdk/objects/base/instance.py
centreon_sdk/objects/base/ldap.py
centreon_sdk/objects/base/macro.py
centreon_sdk/objects/base/poller.py
centreon_sdk/objects/base/real_time_acknowledgement.py
centreon_sdk/objects/base/real_time_downtime.py
centreon_sdk/objects/base/resource_cfg.py
centreon_sdk/objects/base/service.py
centreon_sdk/objects/base/service_category.py
centreon_sdk/objects/base/service_group.py
centreon_sdk/objects/base/service_status.py
centreon_sdk/objects/base/service_template.py
centreon_sdk/objects/base/settings.py
centreon_sdk/objects/base/time_period.py
centreon_sdk/objects/base/trap.py
centreon_sdk/objects/base/vendor.py
centreon_sdk/objects/extended/__init__.py
centreon_sdk/util/__init__.py
centreon_sdk/util/config.py
centreon_sdk/util/method_utils.py