Metadata-Version: 2.1
Name: centreon-sdk
Version: 0.2.1
Summary: A SDK for python to communicate with Centreon
Home-page: https://github.com/myOmikron/PythonCentreonSDK
Author: Niklas Pfister
Author-email: contact@omikron.pw
License: UNKNOWN
Platform: UNKNOWN
Classifier: Programming Language :: Python :: 3
Classifier: License :: OSI Approved :: GNU General Public License v2 or later (GPLv2+)
Classifier: Operating System :: OS Independent
Requires-Python: >=3.6
